oceanai/__init__.py
oceanai/modules/__init__.py
oceanai/modules/core/__init__.py
oceanai/modules/core/core.py
oceanai/modules/core/exceptions.py
oceanai/modules/core/language.py
oceanai/modules/core/messages.py
oceanai/modules/core/settings.py
oceanai/modules/lab/__init__.py
oceanai/modules/lab/audio.py
oceanai/modules/lab/build.py
oceanai/modules/lab/download.py
oceanai/modules/lab/prediction.py
oceanai/modules/lab/text.py
oceanai/modules/lab/unzip.py
oceanai/modules/lab/video.py
oceanai/modules/lab/architectures/__init__.py
oceanai/modules/lab/architectures/audio_architectures.py
oceanai/modules/lab/architectures/fusion_architectures.py
oceanai/modules/lab/architectures/text_architectures.py
oceanai/modules/lab/architectures/utils.py
oceanai/modules/lab/architectures/video_architectures.py
oceanai/modules/locales/en/LC_MESSAGES/base.mo
oceanai/modules/locales/ru/LC_MESSAGES/base.mo
test/__init__.py
test/unit_tests_fi_en.py
test/unit_tests_mupta_ru.py
oceanai-1.0.0a48.dist-info/LICENSE
oceanai-1.0.0a48.dist-info/METADATA
oceanai-1.0.0a48.dist-info/WHEEL
oceanai-1.0.0a48.dist-info/top_level.txt
oceanai-1.0.0a48.dist-info/RECORD
