Metadata-Version: 2.1
Name: oceanai
Version: 1.0.0a48
Summary: OCEAN-AI
Home-page: https://github.com/DmitryRyumin/oceanai
Author: Elena Ryumina, Dmitry Ryumin, Alexey Karpov
Author-email: ryumina_ev@mail.ru, dl_03.03.1991@mail.ru, karpov@iias.spb.su
Maintainer: Elena Ryumina, Dmitry Ryumin
Maintainer-email: ryumina_ev@mail.ru, dl_03.03.1991@mail.ru
License: BSD License
Project-URL: Bug Reports, https://github.com/DmitryRyumin/oceanai/issues
Project-URL: Documentation, https://oceanai.readthedocs.io
Project-URL: Source Code, https://github.com/DmitryRyumin/oceanai/tree/main/oceanai
Project-URL: Download, https://github.com/DmitryRyumin/oceanai/tags
Keywords: OCEAN-AI,MachineLearning,Statistics,ComputerVision,ArtificialIntelligence,Preprocessing
Classifier: Development Status :: 3 - Alpha
Classifier: Natural Language :: Russian
Classifier: Natural Language :: English
Classifier: Intended Audience :: Developers
Classifier: Intended Audience :: Education
Classifier: Intended Audience :: End Users/Desktop
Classifier: Intended Audience :: Science/Research
Classifier: Intended Audience :: Information Technology
Classifier: Intended Audience :: Science/Research
Classifier: License :: OSI Approved :: BSD License
Classifier: Programming Language :: Python
Classifier: Programming Language :: Python :: 3
Classifier: Programming Language :: Python :: 3.9
Classifier: Programming Language :: Python :: 3.10
Classifier: Programming Language :: Python :: 3.11
Classifier: Programming Language :: Python :: 3.12
Classifier: Programming Language :: Python :: 3 :: Only
Classifier: Programming Language :: Python :: Implementation :: CPython
Classifier: Topic :: Scientific/Engineering
Classifier: Topic :: Scientific/Engineering :: Mathematics
Classifier: Topic :: Scientific/Engineering :: Artificial Intelligence
Classifier: Topic :: Scientific/Engineering :: Image Processing
Classifier: Topic :: Scientific/Engineering :: Image Recognition
Classifier: Topic :: Software Development
Classifier: Topic :: Software Development :: Libraries
Classifier: Topic :: Software Development :: Libraries :: Python Modules
Classifier: Topic :: Documentation
Classifier: Topic :: Documentation :: Sphinx
Classifier: Topic :: Multimedia :: Sound/Audio
Classifier: Topic :: Multimedia :: Sound/Audio :: Analysis
Classifier: Topic :: Multimedia :: Sound/Audio :: Speech
Classifier: Topic :: Software Development :: Libraries
Classifier: Topic :: Software Development :: Libraries :: Python Modules
Classifier: Topic :: Software Development :: Localization
Classifier: Topic :: Utilities
Classifier: Operating System :: MacOS :: MacOS X
Classifier: Operating System :: Microsoft :: Windows
Classifier: Operating System :: POSIX :: Linux
Classifier: Framework :: Jupyter
Classifier: Framework :: Jupyter :: JupyterLab :: 4
Classifier: Framework :: Sphinx
Requires-Python: >=3.9, <4
License-File: LICENSE
Requires-Dist: ipython >=8.18.1
Requires-Dist: jupyterlab ==4.2.5
Requires-Dist: numpy >=1.23.5
Requires-Dist: scipy >=1.13.1
Requires-Dist: pandas >=2.2.3
Requires-Dist: requests >=2.32.3
Requires-Dist: opensmile >=2.5.0
Requires-Dist: librosa >=0.10.2.post1
Requires-Dist: audioread >=3.0.1
Requires-Dist: scikit-learn >=1.5.2
Requires-Dist: opencv-contrib-python >=4.10.0.84
Requires-Dist: mediapipe >=0.10.14
Requires-Dist: liwc >=0.5.0
Requires-Dist: transformers ==4.45.1
Requires-Dist: sentencepiece >=0.2.0
Requires-Dist: torch >=2.2.2
Requires-Dist: torchaudio >=2.2.2
Requires-Dist: torchvision >=0.17.2
Requires-Dist: sacremoses >=0.1.1
Requires-Dist: gradio >=5.6.0
